jal/__init__.py
jal/constants.py
jal/jal.py
jal/jal_init.sql
jal/data_import/__init__.py
jal/data_import/category_recognizer.py
jal/data_import/downloader.py
jal/data_import/slips.py
jal/data_import/slips_tax.py
jal/data_import/statements.py
jal/db/__init__.py
jal/db/backup_restore.py
jal/db/helpers.py
jal/db/ledger.py
jal/db/routines.py
jal/languages/en.png
jal/languages/en.qm
jal/languages/ru.png
jal/languages/ru.qm
jal/reports/__init__.py
jal/reports/dlsg.py
jal/reports/helpers.py
jal/reports/reports.py
jal/reports/taxes.py
jal/ui/__init__.py
jal/ui/ui_abort_window.py
jal/ui/ui_add_asset_dlg.py
jal/ui/ui_login_fns_dlg.py
jal/ui/ui_main_window.py
jal/ui/ui_rebuild_window.py
jal/ui/ui_reference_data_dlg.py
jal/ui/ui_select_account_dlg.py
jal/ui/ui_slip_import_dlg.py
jal/ui/ui_tax_export_dlg.py
jal/ui/ui_update_quotes_window.py
jal/ui_custom/__init__.py
jal/ui_custom/account_select.py
jal/ui_custom/amount_editor.py
jal/ui_custom/helpers.py
jal/ui_custom/log_viewer.py
jal/ui_custom/reference_data.py
jal/ui_custom/reference_selector.py
jal/ui_custom/table_view_config.py
jal/updates/__init__.py
jal/updates/delta_schema_10.sql
jal/updates/delta_schema_11.sql
jal/updates/delta_schema_12.sql
jal/updates/update_db_schema.py
jal/widgets/__init__.py
jal/widgets/main_window.py
jal/widgets/mapper_delegate.py
jal/widgets/operations.py
jal/widgets/view_delegate.py
jal-2021.1.1.dist-info/METADATA
jal-2021.1.1.dist-info/WHEEL
jal-2021.1.1.dist-info/entry_points.txt
jal-2021.1.1.dist-info/top_level.txt
jal-2021.1.1.dist-info/RECORD
