Metadata-Version: 2.1
Name: jal
Version: 2021.1.1
Summary: Just Another Ledger - project to track personal financial records
Home-page: https://github.com/titov-vv/jal
Author-email: jal@gmx.ru
License: UNKNOWN
Platform: UNKNOWN
Classifier: Development Status :: 2 - Pre-Alpha
Classifier: Topic :: Office/Business
Classifier: Topic :: Office/Business :: Financial
Classifier: Topic :: Office/Business :: Financial :: Accounting
Classifier: Topic :: Office/Business :: Financial :: Investment
Classifier: License :: OSI Approved :: GNU General Public License v3 (GPLv3)
Classifier: Operating System :: OS Independent
Classifier: Programming Language :: Python
Requires-Python: >=3.8.1
Requires-Dist: lxml
Requires-Dist: pandas
Requires-Dist: PySide2 (>=5.15.2)
Requires-Dist: requests
Requires-Dist: XlsxWriter
